FinAnalytics/__init__.py
FinAnalytics/A/__init__.py
FinAnalytics/A/constants.py
FinAnalytics/A/DB/__init__.py
FinAnalytics/A/DB/LoadRecords.py
FinAnalytics/A/HelperScripts/__init__.py
FinAnalytics/A/HelperScripts/create_finalytics_tasks_for_lambda.py
FinAnalytics/A/HelperScripts/create_transactions_table.py
FinAnalytics/A/HelperScripts/create_upload_tasks_in_bucket.py
FinAnalytics/A/HelperScripts/unlock_delete_transactions.py
FinAnalytics/A/LambdaFunctions/__init__.py
FinAnalytics/A/LambdaFunctions/processPDFBankStatements.py
FinAnalytics/E/__init__.py
FinAnalytics/E/BankStatement/__init__.py
FinAnalytics/E/BankStatement/extract_pdf.py
FinAnalytics/E/BankStatement/load_extractor.py
FinAnalytics/E/BankStatement/train_data.cor
FinAnalytics/E/BankStatement/train_model.py
FinAnalytics/T/__init__.py
FinAnalytics/T/BankStatements/__init__.py
FinAnalytics/T/BankStatements/understandExchanges.py
FinAnalytics/types_used.py
finanalytics-0.5.1.dist-info/METADATA
finanalytics-0.5.1.dist-info/WHEEL
finanalytics-0.5.1.dist-info/RECORD
