Metadata-Version: 2.3
Name: FinAnalytics
Version: 0.5.1
Summary: Package to analyze your personal finances and some utils to perform ETL Operations as well
License: MIT
Author: Rahul
Author-email: saihanumarahul66@gmail.com
Requires-Python: >=3.11,<3.13
Classifier: License :: OSI Approved :: MIT License
Classifier: Programming Language :: Python :: 3
Classifier: Programming Language :: Python :: 3.11
Classifier: Programming Language :: Python :: 3.12
Requires-Dist: aws-lambda-typing (>=2.20.0,<3.0.0)
Requires-Dist: boto3 (>=1.38.23,<2.0.0)
Requires-Dist: countryinfo (>=0.1.2,<0.2.0)
Requires-Dist: dateparser (>=1.2.1,<2.0.0)
Requires-Dist: geopy (>=2.4.1,<3.0.0)
Requires-Dist: loguru (>=0.7.3,<0.8.0)
Requires-Dist: pandas (>=2.2.3,<3.0.0)
Requires-Dist: pdfplumber (>=0.11.6,<0.12.0)
Requires-Dist: price-parser (>=0.4.0,<0.5.0)
Requires-Dist: python-dotenv (>=1.1.0,<2.0.0)
Requires-Dist: rapidfuzz (>=3.13.0,<4.0.0)
Requires-Dist: requests (>=2.32.3,<3.0.0)
Requires-Dist: spacy (>=3.8.5,<4.0.0)
Requires-Dist: timezonefinder (>=6.5.9,<7.0.0)
Requires-Dist: tldextract (>=5.3.0,<6.0.0)
